LICENSE
README.md
setup.py
nligraphspacy/NLIGRAPH.py
nligraphspacy/__init__.py
nligraphspacy.egg-info/PKG-INFO
nligraphspacy.egg-info/SOURCES.txt
nligraphspacy.egg-info/dependency_links.txt
nligraphspacy.egg-info/not-zip-safe
nligraphspacy.egg-info/requires.txt
nligraphspacy.egg-info/top_level.txt