Metadata-Version: 2.1
Name: nligraphspacy
Version: 1.1.3
Summary: Knowledge graph using Spacy NLP
Home-page: https://github.com/Vishnunkumar/nligraphspacy/
Author: Vishnu Nandakumar
Author-email: nkumarvishnu25@gmail.com
License: MIT license
Keywords: spacy nli keywords entities
Classifier: Development Status :: 3 - Alpha
Classifier: Intended Audience :: Developers
Classifier: Topic :: Software Development :: Build Tools
Classifier: License :: OSI Approved :: MIT License
Classifier: Programming Language :: Python :: 3
Classifier: Programming Language :: Python :: 3.4
Classifier: Programming Language :: Python :: 3.5
Classifier: Programming Language :: Python :: 3.6
License-File: LICENSE
